dataclass_plus/__init__.py
test/__init__.py
test/test_dataclass_plus.py
dataclass_plus-2.0.0.dist-info/LICENSE
dataclass_plus-2.0.0.dist-info/METADATA
dataclass_plus-2.0.0.dist-info/WHEEL
dataclass_plus-2.0.0.dist-info/top_level.txt
dataclass_plus-2.0.0.dist-info/RECORD
