Metadata-Version: 2.1
Name: dataclass-plus
Version: 2.0.0
Summary: The dataclass_plus is a fastest type validation library for the dataclass
Home-page: https://github.com/muhammetenes/dataclass_plus
Author: Muhammet Enes Aksu
Author-email: muhammetenesak@gmail.com
License: Apache 2
Platform: UNKNOWN
Classifier: License :: OSI Approved :: Apache Software License
Classifier: Programming Language :: Python :: 3.6
Classifier: Programming Language :: Python :: 3.7
Classifier: Programming Language :: Python :: 3.8
Classifier: Operating System :: POSIX
Classifier: Operating System :: MacOS :: MacOS X
Classifier: Operating System :: Microsoft :: Windows
Classifier: License :: OSI Approved :: Apache Software License
Requires-Python: >=3.7.0
